siso/code_outputs/siso_reg.v
module siso_reg (
    input clk,
    input rst,
    input serial_in,
    output reg serial_out
);

    reg [3:0] shift_reg;

    always @(posedge clk or posedge rst) begin
        if (rst) begin
            shift_reg <= 4'b0000;
        end else begin
            shift_reg <= {shift_reg[2:0], serial_in};  
        end
    end

    always @(*) begin
        serial_out = shift_reg[3];  
    end

endmodule

siso/code_outputs/tb_siso.v
module tb_siso;
    reg clk;
    reg rst;
    reg serial_in;
    wire serial_out;

    siso_reg uut (
        .clk(clk),
        .rst(rst),
        .serial_in(serial_in),
        .serial_out(serial_out)
    );

    always #10 clk = ~clk;

    initial begin
        $dumpfile("tb_siso_out.vcd");
        $dumpvars(0, tb_siso);

        clk = 0;
        rst = 1;
        serial_in = 0;
        #20;

        rst = 0;
        
        // Send 4 bits serially: 1 0 1 1
        serial_in = 1; #20;
        serial_in = 0; #20;
        serial_in = 1; #20;
        serial_in = 1; #20;

        #40 $finish;
    end
endmodule

siso/code_outputs/tb_siso_out.vcd
$date
	Thu Jun 26 17:38:08 2025
$end
$version
	Icarus Verilog
$end
$timescale
	1s
$end
$scope module tb_siso $end
$var wire 1 ! serial_out $end
$var reg 1 " clk $end
$var reg 1 # rst $end
$var reg 1 $ serial_in $end
$scope module uut $end
$var wire 1 " clk $end
$var wire 1 # rst $end
$var wire 1 $ serial_in $end
$var reg 1 ! serial_out $end
$var reg 4 % shift_reg [3:0] $end
$upscope $end
$upscope $end
$enddefinitions $end
#0
$dumpvars
b0 %
0$
1#
0"
0!
$end
#10
1"
#20
0"
1$
0#
#30
b1 %
1"
#40
0"
0$
#50
b10 %
1"
#60
0"
1$
#70
b101 %
1"
#80
0"
#90
1!
b1011 %
1"
#100
0"
#110
0!
b111 %
1"
#120
0"
#130
1!
b1111 %
1"
