PIPO/code_and_output_files/d_ff.v
module d_ff(
    input d , clk , rst , set , 
    output reg q,
    output q_bar
);

always @(posedge clk  or posedge rst or posedge set )
begin 
    if ( rst )
    begin 
        q <= 0 ;
    end
    else if (set )
    begin 
        q <= 1 ;
    end
    else begin 
        q <= d ;
    end 
end
assign q_bar = ~q ;
endmodule

PIPO/code_and_output_files/pipo_reg.v
module pipo_reg (
    input clk , rst , 
    input  d0 , d1 , d2 , d3 ,
      output wire q0, q1, q2, q3
);
wire q3_bar , q2_bar , q1_bar , q0_bar ;
wire set = 0 ;


d_ff dff0 ( .clk (clk) ,.rst(rst) ,.set(set) ,.q_bar(q0_bar) ,.d(d0) ,.q(q0));
d_ff dff1 ( .clk (clk) ,.rst(rst) ,.set(set) ,.q_bar(q1_bar) ,.d(d1) ,.q(q1));
d_ff dff2 ( .clk (clk) ,.rst(rst) ,.set(set) ,.q_bar(q2_bar) ,.d(d2) ,.q(q2));
d_ff dff3 ( .clk (clk) ,.rst(rst) ,.set(set) ,.q_bar(q3_bar) ,.d(d3) ,.q(q3));
endmodule

PIPO/code_and_output_files/tb_pipo_reg.v
module tb_pipo_reg;
reg clk , rst , d0 , d1, d2 , d3;
wire q0 ,q1 ,q2 , q3 ;

pipo_reg uut (
    .clk(clk),
    .rst(rst),
    .d0 (d0),
    .d1(d1),
    .d2(d2),
    .d3(d3),
    .q0(q0),
    .q1(q1),
    .q2(q2),
    .q3(q3)
);

always #5 clk = ~clk ;

initial begin
    $dumpfile ("pipo.vcd");
    $dumpvars ( 0 , tb_pipo_reg);
    clk = 0 ; 
    rst = 1 ;
    # 10 ;
    rst = 0 ;


    //random function
    repeat (10) begin 
        d0 = $random %2 ;
        d1= $random %2 ;
        d2 = $random %2 ;
        d3 = $random %2 ;
#10;
end
$finish ;
end 
endmodule

PIPO/code_and_output_files/pipo.vcd
$date
	Mon Jun 23 17:17:58 2025
$end
$version
	Icarus Verilog
$end
$timescale
	1s
$end
$scope module tb_pipo_reg $end
$var wire 1 ! q3 $end
$var wire 1 " q2 $end
$var wire 1 # q1 $end
$var wire 1 $ q0 $end
$var reg 1 % clk $end
$var reg 1 & d0 $end
$var reg 1 ' d1 $end
$var reg 1 ( d2 $end
$var reg 1 ) d3 $end
$var reg 1 * rst $end
$scope module uut $end
$var wire 1 % clk $end
$var wire 1 & d0 $end
$var wire 1 ' d1 $end
$var wire 1 ( d2 $end
$var wire 1 ) d3 $end
$var wire 1 * rst $end
$var wire 1 + set $end
$var wire 1 , q3_bar $end
$var wire 1 ! q3 $end
$var wire 1 - q2_bar $end
$var wire 1 " q2 $end
$var wire 1 . q1_bar $end
$var wire 1 # q1 $end
$var wire 1 / q0_bar $end
$var wire 1 $ q0 $end
$scope module dff0 $end
$var wire 1 % clk $end
$var wire 1 & d $end
$var wire 1 / q_bar $end
$var wire 1 * rst $end
$var wire 1 + set $end
$var reg 1 $ q $end
$upscope $end
$scope module dff1 $end
$var wire 1 % clk $end
$var wire 1 ' d $end
$var wire 1 . q_bar $end
$var wire 1 * rst $end
$var wire 1 + set $end
$var reg 1 # q $end
$upscope $end
$scope module dff2 $end
$var wire 1 % clk $end
$var wire 1 ( d $end
$var wire 1 - q_bar $end
$var wire 1 * rst $end
$var wire 1 + set $end
$var reg 1 " q $end
$upscope $end
$scope module dff3 $end
$var wire 1 % clk $end
$var wire 1 ) d $end
$var wire 1 , q_bar $end
$var wire 1 * rst $end
$var wire 1 + set $end
$var reg 1 ! q $end
$upscope $end
$upscope $end
$upscope $end
$enddefinitions $end
#0
$dumpvars
1/
1.
1-
1,
0+
1*
x)
x(
x'
x&
0%
0$
0#
0"
0!
$end
#5
1%
#10
0%
1)
1(
1'
0&
0*
#15
0.
0-
0,
1#
1"
1!
1%
#20
0%
0)
1&
#25
1,
0/
0!
1$
1%
#30
0%
1)
0(
#35
1-
0,
0"
1!
1%
#40
0%
0)
1(
0'
#45
1,
0-
1.
0!
1"
0#
1%
#50
0%
1)
#55
0,
1!
1%
#60
0%
0)
0(
1'
0&
#65
1,
1-
0.
1/
0!
0"
1#
0$
1%
#70
0%
1)
#75
0,
1!
1%
#80
0%
0)
1(
1&
#85
1,
0-
0/
0!
1"
1$
1%
#90
0%
1)
0(
0'
0&
#95
1/
1.
1-
0,
0$
0#
0"
1!
1%
#100
0%
1(
1'
#105
0-
0.
1"
1#
1%
